setup.py
LocationWebApp/flaskApp.py
LocationWebApp/serve.py
LocationWebApp.egg-info/PKG-INFO
LocationWebApp.egg-info/SOURCES.txt
LocationWebApp.egg-info/dependency_links.txt
LocationWebApp.egg-info/requires.txt
LocationWebApp.egg-info/top_level.txt