Metadata-Version: 1.1
Name: LocationWebApp
Version: 3.1.2
Summary: A web-application to show your current location on a Google Map & to obtain location data such as latitude, longitude & zip-code
Home-page: http://savithruml.github.io/LocationWebApp/
Author: Savithru Lokanath
Author-email: savithru@icloud.com
License: MIT
Download-URL: https://github.com/savithruml/LocationWebApp/tarball/master
Platform: UNKNOWN
Classifier: License :: OSI Approved :: MIT License
Classifier: Programming Language :: Python :: 3
Classifier: Programming Language :: Python :: 3.3
Classifier: Programming Language :: Python :: 3.4
Classifier: Programming Language :: Python :: 3.5
